booking/__init__.py
booking/clients/__init__.py
booking/clients/booking.py
booking/clients/customer.py
booking/clients/provider.py
booking/clients/resource.py
radex_booking/__init__.py
radex_booking/exceptions.py
radex_booking/clients/__init__.py
radex_booking/clients/booking.py
radex_booking/clients/customer.py
radex_booking/clients/provider.py
radex_booking/clients/resource.py
radex_booking-2025.10.17a1.dist-info/licenses/LICENSE
radex_booking-2025.10.17a1.dist-info/METADATA
radex_booking-2025.10.17a1.dist-info/WHEEL
radex_booking-2025.10.17a1.dist-info/top_level.txt
radex_booking-2025.10.17a1.dist-info/RECORD
