Metadata-Version: 2.4
Name: radex_booking
Version: 2025.10.17a1
Summary: Python API client for radex booking service
Author-email: Ernesto Santana <nesti.s.dev@gmail.com>
License-Expression: MIT
Project-URL: homepage, https://github.com/radex-tech/booking-client-py
Project-URL: source, https://github.com/radex-tech/booking-client-py
Project-URL: changelog, https://github.com/radex-tech/booking-client-py/blob/master/CHANGELOG.md
Project-URL: documentation, https://github.com/radex-tech/booking-client-py/wiki
Project-URL: issues, https://github.com/radex-tech/booking-client-py/issues
Keywords: radex,booking
Classifier: Development Status :: 4 - Beta
Classifier: Intended Audience :: Developers
Classifier: Operating System :: OS Independent
Classifier: Programming Language :: Python :: 3
Classifier: Topic :: Internet :: WWW/HTTP :: Dynamic Content
Classifier: Topic :: Software Development :: Libraries
Requires-Python: >=3.10
License-File: LICENSE
Requires-Dist: httpx
Dynamic: license-file
Dynamic: requires-dist
